littlebrother/__init__.py
littlebrother/__main__.py
littlebrother/humanize.py
littlebrother/plugins/__init__.py
littlebrother/plugins/av.py
littlebrother/plugins/html.py
littlebrother/plugins/image.py
littlebrother/plugins/text.py
littlebrother/test/__init__.py
littlebrother/test/helpers.py
littlebrother/test/test_av.py
littlebrother/test/test_html.py
littlebrother/test/test_http.py
littlebrother/test/test_humanize.py
littlebrother/test/test_image.py
littlebrother/test/test_text.py
littlebrother/test/data/html-meta-refresh
littlebrother/test/data/html-meta-refresh-long
littlebrother/test/data/html-simple
littlebrother/test/data/text-bad-encoding
littlebrother/test/data/text-simple
littlebrother-0.2.dist-info/DESCRIPTION.rst
littlebrother-0.2.dist-info/METADATA
littlebrother-0.2.dist-info/RECORD
littlebrother-0.2.dist-info/WHEEL
littlebrother-0.2.dist-info/metadata.json
littlebrother-0.2.dist-info/top_level.txt
