Metadata-Version: 2.0
Name: littlebrother
Version: 0.2
Summary: An HTTP document title extractor for Twisted Web
Home-page: https://github.com/kxz/littlebrother
Author: Kevin Xiwei Zheng
Author-email: blankplacement+littlebrother@gmail.com
License: X11
Platform: UNKNOWN
Requires-Dist: Twisted (>=16.0.0)
Requires-Dist: ipaddress
Requires-Dist: pyOpenSSL
Requires-Dist: service-identity
Provides-Extra: av
Requires-Dist: av; extra == 'av'
Provides-Extra: html
Requires-Dist: beautifulsoup4; extra == 'html'
Provides-Extra: image
Requires-Dist: Pillow; extra == 'image'
